ai_audit_sdk/__init__.py
ai_audit_sdk/audit_logger.py
ai_audit_sdk/__pycache__/__init__.cpython-313.pyc
ai_audit_sdk/__pycache__/audit_logger.cpython-313.pyc
ai_audit_sdk-1.0.1.dist-info/METADATA
ai_audit_sdk-1.0.1.dist-info/WHEEL
ai_audit_sdk-1.0.1.dist-info/top_level.txt
ai_audit_sdk-1.0.1.dist-info/RECORD
