Metadata-Version: 2.4
Name: ai-audit-sdk
Version: 1.0.1
Summary: SDK for logging AI/ML decisions with compliance tracking
Home-page: https://github.com/aiaudit/python-sdk
Author: AI Audit Trail
Author-email: AI Audit Trail <support@explainable-ai.dev>
Maintainer-email: AI Audit Trail <support@explainable-ai.dev>
License: MIT
Project-URL: Homepage, https://github.com/appdroidinc/TrailJustifier
Project-URL: Repository, https://github.com/appdroidinc/TrailJustifier
Project-URL: Issues, https://github.com/appdroidinc/TrailJustifier/issues
Project-URL: Documentation, https://docs.aiaudit.com
Keywords: ai,audit,compliance,gdpr,ai-act,logging,ml,openai
Classifier: Development Status :: 4 - Beta
Classifier: Intended Audience :: Developers
Classifier: License :: OSI Approved :: MIT License
Classifier: Operating System :: OS Independent
Classifier: Programming Language :: Python :: 3
Classifier: Programming Language :: Python :: 3.8
Classifier: Programming Language :: Python :: 3.9
Classifier: Programming Language :: Python :: 3.10
Classifier: Programming Language :: Python :: 3.11
Classifier: Programming Language :: Python :: 3.12
Classifier: Topic :: Software Development :: Libraries :: Python Modules
Classifier: Topic :: Scientific/Engineering :: Artificial Intelligence
Requires-Python: >=3.7
Requires-Dist: requests>=2.25.0
Provides-Extra: dev
Requires-Dist: pytest>=6.0; extra == "dev"
Requires-Dist: pytest-cov>=2.0; extra == "dev"
Requires-Dist: black>=21.0; extra == "dev"
Requires-Dist: flake8>=3.8; extra == "dev"
Requires-Dist: build>=0.8.0; extra == "dev"
Requires-Dist: twine>=4.0.0; extra == "dev"
Dynamic: author
Dynamic: home-page
Dynamic: requires-python
